django_dynamic_model_admin/__init__.py
django_dynamic_model_admin/admin.py
django_dynamic_model_admin/apps.py
django_dynamic_model_admin/models.py
django_dynamic_model_admin/tests.py
django_dynamic_model_admin/types.py
django_dynamic_model_admin/views.py
django_dynamic_model_admin/locale/zh_hans/LC_MESSAGES/django.mo
django_dynamic_model_admin/locale/zh_hans/LC_MESSAGES/django.po
django_dynamic_model_admin/migrations/__init__.py
django_dynamic_model_admin/static/django-dynamic-model-admin/css/data-admin.css
django_dynamic_model_admin/static/django-dynamic-model-admin/css/modeldefinition-admin.css
django_dynamic_model_admin/templates/django-dynamic-model-admin/data/data-css.css
django_dynamic_model_admin-0.2.2.dist-info/LICENSE
django_dynamic_model_admin-0.2.2.dist-info/METADATA
django_dynamic_model_admin-0.2.2.dist-info/WHEEL
django_dynamic_model_admin-0.2.2.dist-info/top_level.txt
django_dynamic_model_admin-0.2.2.dist-info/RECORD
