Metadata-Version: 2.1
Name: django-dynamic-model-admin
Version: 0.2.2
Summary: Define new type model in Django's admin site. New type model can be managed in admin site, and also provide the auto generated ModelForm.
Home-page: UNKNOWN
Author: zencore
Author-email: dobetter@zencore.cn
License: MIT
Keywords: django admin extentions,django dynamic model admin
Platform: UNKNOWN
Classifier: Development Status :: 5 - Production/Stable
Classifier: Intended Audience :: Developers
Classifier: Topic :: Software Development :: Libraries :: Python Modules
Classifier: License :: OSI Approved :: MIT License
Classifier: Programming Language :: Python :: 3
Classifier: Programming Language :: Python :: 3 :: Only
License-File: LICENSE
Requires-Dist: django
Requires-Dist: django-mptt
Requires-Dist: django-cascading-dropdown-widget (>=0.2.0)
Requires-Dist: django-dynamic-resource-admin (>=0.1.0)
Requires-Dist: django-tabbed-changeform-admin (>=0.1.1)
Requires-Dist: django-gazing-select-widget (>=0.1.2)
Requires-Dist: django-yearmonth-widget
